z4/__init__.py
z4_solver-2024.12.14.1.dist-info/METADATA
z4_solver-2024.12.14.1.dist-info/WHEEL
z4_solver-2024.12.14.1.dist-info/licenses/LICENSE
z4_solver-2024.12.14.1.dist-info/RECORD
