Metadata-Version: 2.3
Name: z4-solver
Version: 2024.12.14.1
Summary: z3++
Project-URL: Repository, https://github.com/Tyilo/z4
Author-email: Asger Hautop Drewsen <asger@tyilo.com>
License: GPL-3.0-only
Requires-Python: >=3.10
Requires-Dist: z3-solver>=4.13.3.0
